MANIFEST.in
README.md
setup.cfg
setup.py
alauda_redis_py_cluster.egg-info/PKG-INFO
alauda_redis_py_cluster.egg-info/SOURCES.txt
alauda_redis_py_cluster.egg-info/dependency_links.txt
alauda_redis_py_cluster.egg-info/requires.txt
alauda_redis_py_cluster.egg-info/top_level.txt
docs/License.txt
docs/authors.rst
docs/release-notes.rst
rediscluster/__init__.py
rediscluster/client.py
rediscluster/connection.py
rediscluster/crc.py
rediscluster/exceptions.py
rediscluster/nodemanager.py
rediscluster/pipeline.py
rediscluster/pubsub.py
rediscluster/utils.py